omnidata_tools/__init__.py
omnidata_tools/_nbdev.py
omnidata_tools/core.py
omnidata_tools/starter_dataset.py
omnidata_tools/dataset/__init__.py
omnidata_tools/dataset/download.py
omnidata_tools/dataset/metadata.py
omnidata_tools/dataset/starter_dataset/__init__.py
omnidata_tools/dataset/starter_dataset/component_datasets/__init__.py
omnidata_tools/dataset/starter_dataset/component_datasets/splits.py
omnidata_tools/dataset/starter_dataset/component_datasets/blendedmvg/__init__.py
omnidata_tools/dataset/starter_dataset/component_datasets/blendedmvg/train_val_test_blendedMVG.csv
omnidata_tools/dataset/starter_dataset/component_datasets/blendedmvs/__init__.py
omnidata_tools/dataset/starter_dataset/component_datasets/blendedmvs/train_val_test_blendedMVS.csv
omnidata_tools/dataset/starter_dataset/component_datasets/gso_in_replica/GSO_LABEL_TRANSFORM.json
omnidata_tools/dataset/starter_dataset/component_datasets/gso_in_replica/__init__.py
omnidata_tools/dataset/starter_dataset/component_datasets/gso_in_replica/classes.json
omnidata_tools/dataset/starter_dataset/component_datasets/gso_in_replica/list_of_objects.json
omnidata_tools/dataset/starter_dataset/component_datasets/gso_in_replica/train_val_test_gso.csv
omnidata_tools/dataset/starter_dataset/component_datasets/hypersim/__init__.py
omnidata_tools/dataset/starter_dataset/component_datasets/hypersim/metadata_images_split_scene_v1.csv
omnidata_tools/dataset/starter_dataset/component_datasets/hypersim/test_hypersim_orig.csv
omnidata_tools/dataset/starter_dataset/component_datasets/hypersim/train_hypersim_orig.csv
omnidata_tools/dataset/starter_dataset/component_datasets/hypersim/train_val_test_hypersim.csv
omnidata_tools/dataset/starter_dataset/component_datasets/hypersim/val_hypersim_orig.csv
omnidata_tools/dataset/starter_dataset/component_datasets/replica/__init__.py
omnidata_tools/dataset/starter_dataset/component_datasets/replica/train_val_test_replica.csv
omnidata_tools-0.0.23.dist-info/LICENSE
omnidata_tools-0.0.23.dist-info/METADATA
omnidata_tools-0.0.23.dist-info/WHEEL
omnidata_tools-0.0.23.dist-info/entry_points.txt
omnidata_tools-0.0.23.dist-info/top_level.txt
omnidata_tools-0.0.23.dist-info/RECORD
