Metadata-Version: 2.1
Name: omnidata-tools
Version: 0.0.23
Summary: Tooling for Omnidata: A Scalable Pipeline for Making Multi-Task Mid-Level Vision Datasets from 3D Scans
Home-page: https://github.com/alexsax/omnidata_tools/tree/main/
Author: Alexander Sax
Author-email: alexanderesax@gmail.com
License: omnidata # Add licenses and see current list in `setup.py`
Keywords: Computer Vison,Vision,Graphics,3D
Platform: UNKNOWN
Classifier: Development Status :: 4 - Beta
Classifier: Intended Audience :: Developers
Classifier: Natural Language :: English
Classifier: Programming Language :: Python :: 3.6
Classifier: Programming Language :: Python :: 3.7
Classifier: Programming Language :: Python :: 3.8
Requires-Python: >=3.6
Requires-Dist: fastcore (>=1.3.21)
Requires-Dist: multiprocess (>=0.70.12.2)
Requires-Dist: aria2p[tui] (>=0.10.4)
Requires-Dist: tqdm
